<?xml version="1.0" encoding="UTF-8"?>
<feature
      id="org.muml.pm.software.feature"
      label="Software Platform Modeling Feature"
      version="1.0.0.qualifier">

   <description>
      Software Platform Modeling Feature
   </description>

   <copyright>
      Copyright (C) Software Engineering Group, Heinz Nixdorf Institute, University of Paderborn, Germany
All rights reserved. This program and the accompanying materials
are made available under the terms of the Eclipse Public License v1.0
which accompanies this distribution, and is available at
http://www.eclipse.org/legal/epl-v10.html
   </copyright>

   <license url="license.html">
      Fujaba Licence Agreement
July 21, 2012

This feature is free software; you can redistribute and/or modify it under the terms of the Eclipse Public License (EPL) as published by the Eclipse Foundation. You can access the full text of the license agreement under http://www.eclipse.org/legal/epl-v10.html
This feature is distributed in the hope that it will be useful, but WITHOUT ANY WARRANTY; without even the implied warranty of MERCHANTABILITY or FITNESS FOR A PARTICULAR PURPOSE.
   </license>

   <requires>
      <import feature="org.muml.core.feature" version="0.5.0"/>
      <import feature="org.muml.pim.feature" version="0.5.0"/>
      <import feature="org.muml.ape.feature" version="0.5.0"/>
      <import feature="org.muml.pm.feature" version="0.5.0.qualifier"/>
   </requires>

   <plugin
         id="org.muml.pm.software"
         download-size="0"
         install-size="0"
         version="0.0.0"
         unpack="false"/>

   <plugin
         id="org.muml.pm.software.edit"
         download-size="0"
         install-size="0"
         version="0.0.0"
         unpack="false"/>

   <plugin
         id="org.muml.pm.software.oslanguage.xtext"
         download-size="0"
         install-size="0"
         version="0.0.0"
         unpack="false"/>

   <plugin
         id="org.muml.pm.software.oslanguage.xtext.ui"
         download-size="0"
         install-size="0"
         version="0.0.0"
         unpack="false"/>

</feature>
